httpmultipart/__init__.py
httpmultipart/main.py
httpmultipart-0.2.0.dist-info/DESCRIPTION.rst
httpmultipart-0.2.0.dist-info/METADATA
httpmultipart-0.2.0.dist-info/RECORD
httpmultipart-0.2.0.dist-info/WHEEL
httpmultipart-0.2.0.dist-info/metadata.json
httpmultipart-0.2.0.dist-info/top_level.txt
