Metadata-Version: 2.0
Name: httpmultipart
Version: 0.2.0
Summary: A httpmultipart post handler
Home-page: https://github.com/tao12345666333/httpmultipart
Author: TaoBeier
Author-email: zhangjintao9020@gmail.com
License: MIT
Platform: any
Classifier: Development Status :: 5 - Production/Stable
Classifier: Intended Audience :: Developers
Classifier: Natural Language :: English
Classifier: License :: OSI Approved :: MIT License
Classifier: Programming Language :: Python
Classifier: Programming Language :: Python :: 2.7
Classifier: Topic :: Software Development :: Libraries
Classifier: Topic :: Software Development :: Libraries :: Python Modules
